{
  "namespace": "NbComponent",
  "fsNamespace": "nb-component",
  "loader": "../nb-component.js",
  "core": "nb-component.xvawsnv3.js",
  "corePolyfilled": "nb-component.qqwhpo4q.js",
  "components": {
    "ht-emoji": {
      "bundleIds": {
        "$": "6kz4elgm"
      },
      "encapsulation": "shadow"
    },
    "ht-richtext-parser": {
      "bundleIds": {
        "$": "lszvyp8p"
      },
      "encapsulation": "shadow"
    },
    "ht-stock": {
      "bundleIds": {
        "$": "vzljrsch"
      },
      "encapsulation": "shadow"
    },
    "ht-subject": {
      "bundleIds": {
        "$": "msgpfhke"
      },
      "encapsulation": "shadow"
    },
    "ht-topic": {
      "bundleIds": {
        "$": "x3ag1mjl"
      },
      "encapsulation": "shadow"
    },
    "nb-actionsheet": {
      "bundleIds": {
        "$": "l5h09gs2"
      },
      "encapsulation": "shadow"
    },
    "nb-affix": {
      "bundleIds": {
        "$": "l5h09gs2"
      },
      "encapsulation": "shadow"
    },
    "nb-badge": {
      "bundleIds": {
        "$": "l5h09gs2"
      },
      "encapsulation": "shadow"
    },
    "nb-canvas-radar": {
      "bundleIds": {
        "$": "l5h09gs2"
      }
    },
    "nb-code-highlight": {
      "bundleIds": {
        "$": "l5h09gs2"
      }
    },
    "nb-list": {
      "bundleIds": {
        "$": "l5h09gs2"
      },
      "encapsulation": "shadow"
    },
    "nb-list-item": {
      "bundleIds": {
        "$": "l5h09gs2"
      },
      "encapsulation": "shadow"
    },
    "nb-marquee": {
      "bundleIds": {
        "$": "l5h09gs2"
      },
      "encapsulation": "shadow"
    },
    "nb-modal": {
      "bundleIds": {
        "$": "j2gopqua"
      },
      "encapsulation": "shadow"
    },
    "nb-pagination": {
      "bundleIds": {
        "$": "l5h09gs2"
      },
      "encapsulation": "shadow"
    },
    "nb-playground": {
      "bundleIds": {
        "$": "l5h09gs2"
      }
    },
    "nb-pull-to-do": {
      "bundleIds": {
        "$": "l5h09gs2"
      },
      "encapsulation": "shadow"
    },
    "nb-refresh": {
      "bundleIds": {
        "$": "jlhuzabx"
      },
      "encapsulation": "shadow"
    },
    "nb-roll-picker": {
      "bundleIds": {
        "$": "l5h09gs2"
      },
      "encapsulation": "shadow"
    },
    "nb-search-bar": {
      "bundleIds": {
        "$": "5jrtfvev"
      },
      "encapsulation": "shadow"
    },
    "nb-svg-icon": {
      "bundleIds": {
        "$": "l5h09gs2"
      },
      "encapsulation": "shadow"
    },
    "nb-switch": {
      "bundleIds": {
        "$": "l5h09gs2"
      },
      "encapsulation": "shadow"
    },
    "nb-toast": {
      "bundleIds": {
        "$": "p7fmnwvw"
      },
      "encapsulation": "shadow"
    }
  }
}